/*    */ package aeolian;
/*    */ 
/*    */ import clojure.lang.AFunction;
/*    */ import clojure.lang.ILookupThunk;
/*    */ import clojure.lang.KeywordLookupSite;
/*    */ import clojure.lang.RT;
/*    */ import clojure.lang.Var;
/*    */ 
/*    */ 
/*    */ 
/*    */ 
/*    */ 
/*    */ 
/*    */ 
/*    */ 
/*    */ 
/*    */ 
/*    */ 
/*    */ 
/*    */ 
/*    */ 
/*    */ 
/*    */ 
/*    */ 
/*    */ 
/*    */ 
/*    */ 
/*    */ 
/*    */ 
/*    */ 
/*    */ 
/*    */ 
/*    */ 
/*    */ 
/*    */ 
/*    */ 
/*    */ 
/*    */ 
/*    */ 
/*    */ 
/*    */ 
/*    */ 
/*    */ 
/*    */ 
/*    */ 
/*    */ 
/*    */ 
/*    */ 
/*    */ 
/*    */ 
/*    */ 
/*    */ 
/*    */ 
/*    */ 
/*    */ 
/*    */ 
/*    */ 
/*    */ 
/*    */ 
/*    */ public final class composer$fn__9801$metrics_to_measure__9806$fn__9807
/*    */   extends AFunction
/*    */ {
/*    */   public composer$fn__9801$metrics_to_measure__9806$fn__9807(Object paramObject1, Object paramObject2, Object paramObject3)
/*    */   {
/* 65 */     this.G__9800 = paramObject1;this.G__9799 = paramObject2;this.G__9798 = paramObject3; } static ILookupThunk __thunk__1__ = __site__1__ = new KeywordLookupSite(RT.keyword(null, "notes")); static final KeywordLookupSite __site__1__; static ILookupThunk __thunk__0__ = __site__0__ = new KeywordLookupSite(RT.keyword(null, "method-length")); static final KeywordLookupSite __site__0__; public static final Var const__4 = (Var)RT.var("aeolian.abc.core", "measure"); public static final Var const__2 = (Var)RT.var("aeolian.abc.notes", "chord-for-method-length"); public static final Var const__1 = (Var)RT.var("aeolian.composer", "find-longest-method-length-in"); public static final Var const__0 = (Var)RT.var("aeolian.composer", "build-measure");
/*    */   Object G__9798;
/*    */   Object G__9799;
/*    */   Object G__9800;
/*    */   
/*    */   /* Error */
/*    */   public Object invoke()
/*    */   {
/*    */     // Byte code:
/*    */     //   0: aload_0
/*    */     //   1: getfield 20	aeolian/composer$fn__9801$metrics_to_measure__9806$fn__9807:G__9798	Ljava/lang/Object;
/*    */     //   4: aload_0
/*    */     //   5: aconst_null
/*    */     //   6: putfield 20	aeolian/composer$fn__9801$metrics_to_measure__9806$fn__9807:G__9798	Ljava/lang/Object;
/*    */     //   9: astore_1
/*    */     //   10: aload_0
/*    */     //   11: getfield 18	aeolian/composer$fn__9801$metrics_to_measure__9806$fn__9807:G__9799	Ljava/lang/Object;
/*    */     //   14: aload_0
/*    */     //   15: aconst_null
/*    */     //   16: putfield 18	aeolian/composer$fn__9801$metrics_to_measure__9806$fn__9807:G__9799	Ljava/lang/Object;
/*    */     //   19: astore_2
/*    */     //   20: aload_0
/*    */     //   21: getfield 16	aeolian/composer$fn__9801$metrics_to_measure__9806$fn__9807:G__9800	Ljava/lang/Object;
/*    */     //   24: aload_0
/*    */     //   25: aconst_null
/*    */     //   26: putfield 16	aeolian/composer$fn__9801$metrics_to_measure__9806$fn__9807:G__9800	Ljava/lang/Object;
/*    */     //   29: astore_3
/*    */     //   30: getstatic 26	aeolian/composer$fn__9801$metrics_to_measure__9806$fn__9807:const__0	Lclojure/lang/Var;
/*    */     //   33: invokevirtual 31	clojure/lang/Var:getRawRoot	()Ljava/lang/Object;
/*    */     //   36: checkcast 33	clojure/lang/IFn
/*    */     //   39: aload_1
/*    */     //   40: aload_2
/*    */     //   41: aload_3
/*    */     //   42: aconst_null
/*    */     //   43: astore_3
/*    */     //   44: invokeinterface 36 4 0
/*    */     //   49: astore 4
/*    */     //   51: getstatic 39	aeolian/composer$fn__9801$metrics_to_measure__9806$fn__9807:const__1	Lclojure/lang/Var;
/*    */     //   54: invokevirtual 31	clojure/lang/Var:getRawRoot	()Ljava/lang/Object;
/*    */     //   57: checkcast 33	clojure/lang/IFn
/*    */     //   60: aload_1
/*    */     //   61: aconst_null
/*    */     //   62: astore_1
/*    */     //   63: invokeinterface 42 2 0
/*    */     //   68: astore 5
/*    */     //   70: getstatic 45	aeolian/composer$fn__9801$metrics_to_measure__9806$fn__9807:const__2	Lclojure/lang/Var;
/*    */     //   73: invokevirtual 31	clojure/lang/Var:getRawRoot	()Ljava/lang/Object;
/*    */     //   76: checkcast 33	clojure/lang/IFn
/*    */     //   79: aload 5
/*    */     //   81: aconst_null
/*    */     //   82: astore 5
/*    */     //   84: aload_2
/*    */     //   85: aconst_null
/*    */     //   86: astore_2
/*    */     //   87: getstatic 49	aeolian/composer$fn__9801$metrics_to_measure__9806$fn__9807:__thunk__0__	Lclojure/lang/ILookupThunk;
/*    */     //   90: dup
/*    */     //   91: aload 4
/*    */     //   93: dup_x2
/*    */     //   94: invokeinterface 54 2 0
/*    */     //   99: dup_x2
/*    */     //   100: if_acmpeq +7 -> 107
/*    */     //   103: pop
/*    */     //   104: goto +25 -> 129
/*    */     //   107: swap
/*    */     //   108: pop
/*    */     //   109: dup
/*    */     //   110: getstatic 58	aeolian/composer$fn__9801$metrics_to_measure__9806$fn__9807:__site__0__	Lclojure/lang/KeywordLookupSite;
/*    */     //   113: swap
/*    */     //   114: invokeinterface 64 2 0
/*    */     //   119: dup
/*    */     //   120: putstatic 49	aeolian/composer$fn__9801$metrics_to_measure__9806$fn__9807:__thunk__0__	Lclojure/lang/ILookupThunk;
/*    */     //   123: swap
/*    */     //   124: invokeinterface 54 2 0
/*    */     //   129: invokeinterface 36 4 0
/*    */     //   134: astore 6
/*    */     //   136: getstatic 67	aeolian/composer$fn__9801$metrics_to_measure__9806$fn__9807:const__4	Lclojure/lang/Var;
/*    */     //   139: invokevirtual 31	clojure/lang/Var:getRawRoot	()Ljava/lang/Object;
/*    */     //   142: checkcast 33	clojure/lang/IFn
/*    */     //   145: aload 6
/*    */     //   147: aconst_null
/*    */     //   148: astore 6
/*    */     //   150: getstatic 70	aeolian/composer$fn__9801$metrics_to_measure__9806$fn__9807:__thunk__1__	Lclojure/lang/ILookupThunk;
/*    */     //   153: dup
/*    */     //   154: aload 4
/*    */     //   156: aconst_null
/*    */     //   157: astore 4
/*    */     //   159: dup_x2
/*    */     //   160: invokeinterface 54 2 0
/*    */     //   165: dup_x2
/*    */     //   166: if_acmpeq +7 -> 173
/*    */     //   169: pop
/*    */     //   170: goto +25 -> 195
/*    */     //   173: swap
/*    */     //   174: pop
/*    */     //   175: dup
/*    */     //   176: getstatic 73	aeolian/composer$fn__9801$metrics_to_measure__9806$fn__9807:__site__1__	Lclojure/lang/KeywordLookupSite;
/*    */     //   179: swap
/*    */     //   180: invokeinterface 64 2 0
/*    */     //   185: dup
/*    */     //   186: putstatic 70	aeolian/composer$fn__9801$metrics_to_measure__9806$fn__9807:__thunk__1__	Lclojure/lang/ILookupThunk;
/*    */     //   189: swap
/*    */     //   190: invokeinterface 54 2 0
/*    */     //   195: invokeinterface 76 3 0
/*    */     //   200: areturn
/*    */     // Line number table:
/*    */     //   Java source line #65	-> byte code offset #0
/*    */     //   Java source line #69	-> byte code offset #36
/*    */     //   Java source line #69	-> byte code offset #44
/*    */     //   Java source line #70	-> byte code offset #57
/*    */     //   Java source line #70	-> byte code offset #63
/*    */     //   Java source line #71	-> byte code offset #76
/*    */     //   Java source line #71	-> byte code offset #87
/*    */     //   Java source line #71	-> byte code offset #93
/*    */     //   Java source line #71	-> byte code offset #129
/*    */     //   Java source line #72	-> byte code offset #142
/*    */     //   Java source line #72	-> byte code offset #150
/*    */     //   Java source line #72	-> byte code offset #159
/*    */     //   Java source line #72	-> byte code offset #195
/*    */     // Local variable table:
/*    */     //   start	length	slot	name	signature
/*    */     //   0	200	0	this	Object
/*    */     //   10	190	1	metrics_in_measure	Object
/*    */     //   20	180	2	composition_key	Object
/*    */     //   30	170	3	method_length	Object
/*    */     //   51	149	4	measure	Object
/*    */     //   70	130	5	current_method_length	Object
/*    */     //   136	64	6	accompanying_chord	Object
/*    */   }
/*    */ }


/* Location:              /home/amarks/code/aeolian/target/aeolian-0.1.1-SNAPSHOT.jar!/aeolian/composer$fn__9801$metrics_to_measure__9806$fn__9807.class
 * Java compiler version: 5 (49.0)
 * JD-Core Version:       0.7.1
 */