/*    */ package aeolian;
/*    */ 
/*    */ import clojure.lang.AFunction;
/*    */ import clojure.lang.RT;
/*    */ import clojure.lang.Var;
/*    */ 
/*    */ 
/*    */ 
/*    */ 
/*    */ 
/*    */ 
/*    */ 
/*    */ 
/*    */ 
/*    */ 
/*    */ 
/*    */ 
/*    */ 
/*    */ 
/*    */ 
/*    */ 
/*    */ 
/*    */ 
/*    */ 
/*    */ 
/*    */ 
/*    */ 
/*    */ 
/*    */ 
/*    */ 
/*    */ 
/*    */ 
/*    */ 
/*    */ 
/*    */ 
/*    */ 
/*    */ 
/*    */ 
/*    */ 
/*    */ 
/*    */ 
/*    */ 
/*    */ 
/*    */ 
/*    */ 
/*    */ 
/*    */ 
/*    */ 
/*    */ 
/*    */ 
/*    */ 
/*    */ 
/*    */ 
/*    */ 
/*    */ 
/*    */ 
/*    */ 
/*    */ 
/*    */ 
/*    */ 
/*    */ 
/*    */ 
/*    */ 
/*    */ 
/*    */ 
/*    */ 
/*    */ 
/*    */ 
/*    */ 
/*    */ 
/*    */ 
/*    */ 
/*    */ 
/*    */ 
/*    */ 
/*    */ 
/*    */ public final class composer$fn__9875$compose__9880$fn__9881
/*    */   extends AFunction
/*    */ {
/*    */   Object G__9873;
/*    */   Object G__9874;
/*    */   
/*    */   public composer$fn__9875$compose__9880$fn__9881(Object paramObject1, Object paramObject2)
/*    */   {
/* 85 */     this.G__9873 = paramObject1;this.G__9874 = paramObject2; } public static final Var const__3 = (Var)RT.var("aeolian.composer", "map-metrics");
/*    */   
/*    */   /* Error */
/*    */   public Object invoke()
/*    */   {
/*    */     // Byte code:
/*    */     //   0: aload_0
/*    */     //   1: getfield 15	aeolian/composer$fn__9875$compose__9880$fn__9881:G__9873	Ljava/lang/Object;
/*    */     //   4: aload_0
/*    */     //   5: aconst_null
/*    */     //   6: putfield 15	aeolian/composer$fn__9875$compose__9880$fn__9881:G__9873	Ljava/lang/Object;
/*    */     //   9: astore_1
/*    */     //   10: aload_0
/*    */     //   11: getfield 17	aeolian/composer$fn__9875$compose__9880$fn__9881:G__9874	Ljava/lang/Object;
/*    */     //   14: aload_0
/*    */     //   15: aconst_null
/*    */     //   16: putfield 17	aeolian/composer$fn__9875$compose__9880$fn__9881:G__9874	Ljava/lang/Object;
/*    */     //   19: astore_2
/*    */     //   20: aload_1
/*    */     //   21: invokestatic 25	clojure/lang/RT:count	(Ljava/lang/Object;)I
/*    */     //   24: i2l
/*    */     //   25: lconst_0
/*    */     //   26: lcmp
/*    */     //   27: ifle +27 -> 54
/*    */     //   30: getstatic 29	aeolian/composer$fn__9875$compose__9880$fn__9881:const__3	Lclojure/lang/Var;
/*    */     //   33: invokevirtual 34	clojure/lang/Var:getRawRoot	()Ljava/lang/Object;
/*    */     //   36: checkcast 36	clojure/lang/IFn
/*    */     //   39: aload_1
/*    */     //   40: aconst_null
/*    */     //   41: astore_1
/*    */     //   42: aload_2
/*    */     //   43: aconst_null
/*    */     //   44: astore_2
/*    */     //   45: invokeinterface 39 3 0
/*    */     //   50: goto +5 -> 55
/*    */     //   53: pop
/*    */     //   54: aconst_null
/*    */     //   55: areturn
/*    */     // Line number table:
/*    */     //   Java source line #85	-> byte code offset #0
/*    */     //   Java source line #86	-> byte code offset #20
/*    */     //   Java source line #86	-> byte code offset #20
/*    */     //   Java source line #86	-> byte code offset #21
/*    */     //   Java source line #87	-> byte code offset #36
/*    */     //   Java source line #87	-> byte code offset #45
/*    */     // Local variable table:
/*    */     //   start	length	slot	name	signature
/*    */     //   0	55	0	this	Object
/*    */     //   10	45	1	metrics	Object
/*    */     //   20	35	2	composition_key	Object
/*    */   }
/*    */ }


/* Location:              /home/amarks/code/aeolian/target/aeolian-0.1.1-SNAPSHOT.jar!/aeolian/composer$fn__9875$compose__9880$fn__9881.class
 * Java compiler version: 5 (49.0)
 * JD-Core Version:       0.7.1
 */