/*    */ package aeolian;
/*    */ 
/*    */ import clojure.lang.AFn;
/*    */ import clojure.lang.AFunction;
/*    */ import clojure.lang.IObj;
/*    */ import clojure.lang.IPersistentMap;
/*    */ import clojure.lang.Keyword;
/*    */ import clojure.lang.RT;
/*    */ import clojure.lang.Symbol;
/*    */ import clojure.lang.Tuple;
/*    */ import clojure.lang.Var;
/*    */ 
/*    */ 
/*    */ 
/*    */ 
/*    */ 
/*    */ 
/*    */ 
/*    */ 
/*    */ 
/*    */ 
/*    */ 
/*    */ 
/*    */ 
/*    */ 
/*    */ 
/*    */ 
/*    */ 
/*    */ 
/*    */ 
/*    */ 
/*    */ 
/*    */ 
/*    */ 
/*    */ 
/*    */ 
/*    */ 
/*    */ 
/*    */ 
/*    */ 
/*    */ 
/*    */ 
/*    */ 
/*    */ 
/*    */ 
/*    */ 
/*    */ 
/*    */ 
/*    */ 
/*    */ 
/*    */ 
/*    */ 
/*    */ 
/*    */ 
/*    */ 
/*    */ 
/*    */ 
/*    */ 
/*    */ 
/*    */ 
/*    */ 
/*    */ 
/*    */ 
/*    */ 
/*    */ 
/*    */ 
/*    */ 
/*    */ 
/*    */ public final class composer$fn__9824$split_metrics_into_equal_measures__9829
/*    */   extends AFunction
/*    */ {
/*    */   public composer$fn__9824$split_metrics_into_equal_measures__9829(Object paramObject1, Object paramObject2, Object paramObject3, Object paramObject4, Object paramObject5)
/*    */   {
/* 74 */     this.input_schema9820 = paramObject1;this.ufv__ = paramObject2;this.input_checker9821 = paramObject3;this.output_checker9822 = paramObject4;this.output_schema9819 = paramObject5; } public static final Keyword const__11 = (Keyword)RT.keyword(null, "output"); public static final Keyword const__10 = (Keyword)RT.keyword(null, "error"); public static final Keyword const__9 = (Keyword)RT.keyword(null, "value"); public static final Keyword const__8 = (Keyword)RT.keyword(null, "schema"); public static final Keyword const__7 = (Keyword)RT.keyword("schema.core", "error"); public static final Keyword const__6 = (Keyword)RT.keyword(null, "type"); public static final Var const__5 = (Var)RT.var("clojure.core", "pr-str"); public static final Var const__4 = (Var)RT.var("schema.utils", "format*"); public static final Var const__3 = (Var)RT.var("clojure.core", "deref"); public static final AFn const__2 = (AFn)((IObj)Symbol.intern(null, "split-metrics-into-equal-measures")).withMeta((IPersistentMap)RT.map(new Object[] { RT.keyword(null, "schema"), Tuple.create(Tuple.create(Symbol.intern(null, "ParsedMetricLine"))) })); public static final Keyword const__1 = (Keyword)RT.keyword(null, "input"); public static final Var const__0 = (Var)RT.var("schema.core", "fn-validator");
/*    */   Object output_schema9819;
/*    */   Object output_checker9822;
/*    */   Object input_checker9821;
/*    */   Object ufv__;
/*    */   Object input_schema9820;
/*    */   
/*    */   /* Error */
/*    */   public Object invoke(Object G__9823)
/*    */   {
/*    */     // Byte code:
/*    */     //   0: aload_0
/*    */     //   1: getfield 20	aeolian/composer$fn__9824$split_metrics_into_equal_measures__9829:ufv__	Ljava/lang/Object;
/*    */     //   4: checkcast 30	java/util/concurrent/atomic/AtomicReference
/*    */     //   7: invokevirtual 34	java/util/concurrent/atomic/AtomicReference:get	()Ljava/lang/Object;
/*    */     //   10: astore_2
/*    */     //   11: aload_2
/*    */     //   12: dup
/*    */     //   13: ifnull +250 -> 263
/*    */     //   16: getstatic 40	java/lang/Boolean:FALSE	Ljava/lang/Boolean;
/*    */     //   19: if_acmpeq +245 -> 264
/*    */     //   22: aload_1
/*    */     //   23: invokestatic 46	clojure/lang/Tuple:create	(Ljava/lang/Object;)Lclojure/lang/IPersistentVector;
/*    */     //   26: astore_3
/*    */     //   27: getstatic 50	aeolian/composer$fn__9824$split_metrics_into_equal_measures__9829:const__0	Lclojure/lang/Var;
/*    */     //   30: invokevirtual 55	clojure/lang/Var:getRawRoot	()Ljava/lang/Object;
/*    */     //   33: dup
/*    */     //   34: ifnull +58 -> 92
/*    */     //   37: getstatic 40	java/lang/Boolean:FALSE	Ljava/lang/Boolean;
/*    */     //   40: if_acmpeq +53 -> 93
/*    */     //   43: getstatic 50	aeolian/composer$fn__9824$split_metrics_into_equal_measures__9829:const__0	Lclojure/lang/Var;
/*    */     //   46: invokevirtual 55	clojure/lang/Var:getRawRoot	()Ljava/lang/Object;
/*    */     //   49: checkcast 57	clojure/lang/IFn
/*    */     //   52: getstatic 61	aeolian/composer$fn__9824$split_metrics_into_equal_measures__9829:const__1	Lclojure/lang/Keyword;
/*    */     //   55: getstatic 65	aeolian/composer$fn__9824$split_metrics_into_equal_measures__9829:const__2	Lclojure/lang/AFn;
/*    */     //   58: aload_0
/*    */     //   59: getfield 18	aeolian/composer$fn__9824$split_metrics_into_equal_measures__9829:input_schema9820	Ljava/lang/Object;
/*    */     //   62: getstatic 68	aeolian/composer$fn__9824$split_metrics_into_equal_measures__9829:const__3	Lclojure/lang/Var;
/*    */     //   65: invokevirtual 55	clojure/lang/Var:getRawRoot	()Ljava/lang/Object;
/*    */     //   68: checkcast 57	clojure/lang/IFn
/*    */     //   71: aload_0
/*    */     //   72: getfield 22	aeolian/composer$fn__9824$split_metrics_into_equal_measures__9829:input_checker9821	Ljava/lang/Object;
/*    */     //   75: invokeinterface 70 2 0
/*    */     //   80: aload_3
/*    */     //   81: aconst_null
/*    */     //   82: astore_3
/*    */     //   83: invokeinterface 73 6 0
/*    */     //   88: pop
/*    */     //   89: goto +171 -> 260
/*    */     //   92: pop
/*    */     //   93: getstatic 68	aeolian/composer$fn__9824$split_metrics_into_equal_measures__9829:const__3	Lclojure/lang/Var;
/*    */     //   96: invokevirtual 55	clojure/lang/Var:getRawRoot	()Ljava/lang/Object;
/*    */     //   99: checkcast 57	clojure/lang/IFn
/*    */     //   102: aload_0
/*    */     //   103: getfield 22	aeolian/composer$fn__9824$split_metrics_into_equal_measures__9829:input_checker9821	Ljava/lang/Object;
/*    */     //   106: invokeinterface 70 2 0
/*    */     //   111: checkcast 57	clojure/lang/IFn
/*    */     //   114: aload_3
/*    */     //   115: invokeinterface 70 2 0
/*    */     //   120: astore 4
/*    */     //   122: aload 4
/*    */     //   124: dup
/*    */     //   125: ifnull +132 -> 257
/*    */     //   128: getstatic 40	java/lang/Boolean:FALSE	Ljava/lang/Boolean;
/*    */     //   131: if_acmpeq +127 -> 258
/*    */     //   134: aload 4
/*    */     //   136: aconst_null
/*    */     //   137: astore 4
/*    */     //   139: astore 5
/*    */     //   141: new 75	clojure/lang/ExceptionInfo
/*    */     //   144: dup
/*    */     //   145: getstatic 78	aeolian/composer$fn__9824$split_metrics_into_equal_measures__9829:const__4	Lclojure/lang/Var;
/*    */     //   148: invokevirtual 55	clojure/lang/Var:getRawRoot	()Ljava/lang/Object;
/*    */     //   151: checkcast 57	clojure/lang/IFn
/*    */     //   154: ldc 80
/*    */     //   156: getstatic 65	aeolian/composer$fn__9824$split_metrics_into_equal_measures__9829:const__2	Lclojure/lang/AFn;
/*    */     //   159: getstatic 83	aeolian/composer$fn__9824$split_metrics_into_equal_measures__9829:const__5	Lclojure/lang/Var;
/*    */     //   162: invokevirtual 55	clojure/lang/Var:getRawRoot	()Ljava/lang/Object;
/*    */     //   165: checkcast 57	clojure/lang/IFn
/*    */     //   168: aload 5
/*    */     //   170: invokeinterface 70 2 0
/*    */     //   175: invokeinterface 86 4 0
/*    */     //   180: checkcast 88	java/lang/String
/*    */     //   183: bipush 8
/*    */     //   185: anewarray 90	java/lang/Object
/*    */     //   188: dup
/*    */     //   189: iconst_0
/*    */     //   190: getstatic 93	aeolian/composer$fn__9824$split_metrics_into_equal_measures__9829:const__6	Lclojure/lang/Keyword;
/*    */     //   193: aastore
/*    */     //   194: dup
/*    */     //   195: iconst_1
/*    */     //   196: getstatic 96	aeolian/composer$fn__9824$split_metrics_into_equal_measures__9829:const__7	Lclojure/lang/Keyword;
/*    */     //   199: aastore
/*    */     //   200: dup
/*    */     //   201: iconst_2
/*    */     //   202: getstatic 99	aeolian/composer$fn__9824$split_metrics_into_equal_measures__9829:const__8	Lclojure/lang/Keyword;
/*    */     //   205: aastore
/*    */     //   206: dup
/*    */     //   207: iconst_3
/*    */     //   208: aload_0
/*    */     //   209: getfield 18	aeolian/composer$fn__9824$split_metrics_into_equal_measures__9829:input_schema9820	Ljava/lang/Object;
/*    */     //   212: aastore
/*    */     //   213: dup
/*    */     //   214: iconst_4
/*    */     //   215: getstatic 102	aeolian/composer$fn__9824$split_metrics_into_equal_measures__9829:const__9	Lclojure/lang/Keyword;
/*    */     //   218: aastore
/*    */     //   219: dup
/*    */     //   220: iconst_5
/*    */     //   221: aload_3
/*    */     //   222: aconst_null
/*    */     //   223: astore_3
/*    */     //   224: aastore
/*    */     //   225: dup
/*    */     //   226: bipush 6
/*    */     //   228: getstatic 105	aeolian/composer$fn__9824$split_metrics_into_equal_measures__9829:const__10	Lclojure/lang/Keyword;
/*    */     //   231: aastore
/*    */     //   232: dup
/*    */     //   233: bipush 7
/*    */     //   235: aload 5
/*    */     //   237: aconst_null
/*    */     //   238: astore 5
/*    */     //   240: aastore
/*    */     //   241: invokestatic 111	clojure/lang/RT:mapUniqueKeys	([Ljava/lang/Object;)Lclojure/lang/IPersistentMap;
/*    */     //   244: checkcast 113	clojure/lang/IPersistentMap
/*    */     //   247: invokespecial 116	clojure/lang/ExceptionInfo:<init>	(Ljava/lang/String;Lclojure/lang/IPersistentMap;)V
/*    */     //   250: checkcast 118	java/lang/Throwable
/*    */     //   253: athrow
/*    */     //   254: goto +6 -> 260
/*    */     //   257: pop
/*    */     //   258: aconst_null
/*    */     //   259: pop
/*    */     //   260: goto +6 -> 266
/*    */     //   263: pop
/*    */     //   264: aconst_null
/*    */     //   265: pop
/*    */     //   266: new 123	aeolian/composer$fn__9824$split_metrics_into_equal_measures__9829$fn__9830
/*    */     //   269: dup
/*    */     //   270: aload_1
/*    */     //   271: aconst_null
/*    */     //   272: astore_1
/*    */     //   273: invokespecial 126	aeolian/composer$fn__9824$split_metrics_into_equal_measures__9829$fn__9830:<init>	(Ljava/lang/Object;)V
/*    */     //   276: checkcast 57	clojure/lang/IFn
/*    */     //   279: invokeinterface 128 1 0
/*    */     //   284: astore_3
/*    */     //   285: aload_2
/*    */     //   286: aconst_null
/*    */     //   287: astore_2
/*    */     //   288: dup
/*    */     //   289: ifnull +241 -> 530
/*    */     //   292: getstatic 40	java/lang/Boolean:FALSE	Ljava/lang/Boolean;
/*    */     //   295: if_acmpeq +236 -> 531
/*    */     //   298: getstatic 50	aeolian/composer$fn__9824$split_metrics_into_equal_measures__9829:const__0	Lclojure/lang/Var;
/*    */     //   301: invokevirtual 55	clojure/lang/Var:getRawRoot	()Ljava/lang/Object;
/*    */     //   304: dup
/*    */     //   305: ifnull +56 -> 361
/*    */     //   308: getstatic 40	java/lang/Boolean:FALSE	Ljava/lang/Boolean;
/*    */     //   311: if_acmpeq +51 -> 362
/*    */     //   314: getstatic 50	aeolian/composer$fn__9824$split_metrics_into_equal_measures__9829:const__0	Lclojure/lang/Var;
/*    */     //   317: invokevirtual 55	clojure/lang/Var:getRawRoot	()Ljava/lang/Object;
/*    */     //   320: checkcast 57	clojure/lang/IFn
/*    */     //   323: getstatic 131	aeolian/composer$fn__9824$split_metrics_into_equal_measures__9829:const__11	Lclojure/lang/Keyword;
/*    */     //   326: getstatic 65	aeolian/composer$fn__9824$split_metrics_into_equal_measures__9829:const__2	Lclojure/lang/AFn;
/*    */     //   329: aload_0
/*    */     //   330: getfield 26	aeolian/composer$fn__9824$split_metrics_into_equal_measures__9829:output_schema9819	Ljava/lang/Object;
/*    */     //   333: getstatic 68	aeolian/composer$fn__9824$split_metrics_into_equal_measures__9829:const__3	Lclojure/lang/Var;
/*    */     //   336: invokevirtual 55	clojure/lang/Var:getRawRoot	()Ljava/lang/Object;
/*    */     //   339: checkcast 57	clojure/lang/IFn
/*    */     //   342: aload_0
/*    */     //   343: getfield 24	aeolian/composer$fn__9824$split_metrics_into_equal_measures__9829:output_checker9822	Ljava/lang/Object;
/*    */     //   346: invokeinterface 70 2 0
/*    */     //   351: aload_3
/*    */     //   352: invokeinterface 73 6 0
/*    */     //   357: pop
/*    */     //   358: goto +169 -> 527
/*    */     //   361: pop
/*    */     //   362: getstatic 68	aeolian/composer$fn__9824$split_metrics_into_equal_measures__9829:const__3	Lclojure/lang/Var;
/*    */     //   365: invokevirtual 55	clojure/lang/Var:getRawRoot	()Ljava/lang/Object;
/*    */     //   368: checkcast 57	clojure/lang/IFn
/*    */     //   371: aload_0
/*    */     //   372: getfield 24	aeolian/composer$fn__9824$split_metrics_into_equal_measures__9829:output_checker9822	Ljava/lang/Object;
/*    */     //   375: invokeinterface 70 2 0
/*    */     //   380: checkcast 57	clojure/lang/IFn
/*    */     //   383: aload_3
/*    */     //   384: invokeinterface 70 2 0
/*    */     //   389: astore 4
/*    */     //   391: aload 4
/*    */     //   393: dup
/*    */     //   394: ifnull +130 -> 524
/*    */     //   397: getstatic 40	java/lang/Boolean:FALSE	Ljava/lang/Boolean;
/*    */     //   400: if_acmpeq +125 -> 525
/*    */     //   403: aload 4
/*    */     //   405: aconst_null
/*    */     //   406: astore 4
/*    */     //   408: astore 5
/*    */     //   410: new 75	clojure/lang/ExceptionInfo
/*    */     //   413: dup
/*    */     //   414: getstatic 78	aeolian/composer$fn__9824$split_metrics_into_equal_measures__9829:const__4	Lclojure/lang/Var;
/*    */     //   417: invokevirtual 55	clojure/lang/Var:getRawRoot	()Ljava/lang/Object;
/*    */     //   420: checkcast 57	clojure/lang/IFn
/*    */     //   423: ldc -123
/*    */     //   425: getstatic 65	aeolian/composer$fn__9824$split_metrics_into_equal_measures__9829:const__2	Lclojure/lang/AFn;
/*    */     //   428: getstatic 83	aeolian/composer$fn__9824$split_metrics_into_equal_measures__9829:const__5	Lclojure/lang/Var;
/*    */     //   431: invokevirtual 55	clojure/lang/Var:getRawRoot	()Ljava/lang/Object;
/*    */     //   434: checkcast 57	clojure/lang/IFn
/*    */     //   437: aload 5
/*    */     //   439: invokeinterface 70 2 0
/*    */     //   444: invokeinterface 86 4 0
/*    */     //   449: checkcast 88	java/lang/String
/*    */     //   452: bipush 8
/*    */     //   454: anewarray 90	java/lang/Object
/*    */     //   457: dup
/*    */     //   458: iconst_0
/*    */     //   459: getstatic 93	aeolian/composer$fn__9824$split_metrics_into_equal_measures__9829:const__6	Lclojure/lang/Keyword;
/*    */     //   462: aastore
/*    */     //   463: dup
/*    */     //   464: iconst_1
/*    */     //   465: getstatic 96	aeolian/composer$fn__9824$split_metrics_into_equal_measures__9829:const__7	Lclojure/lang/Keyword;
/*    */     //   468: aastore
/*    */     //   469: dup
/*    */     //   470: iconst_2
/*    */     //   471: getstatic 99	aeolian/composer$fn__9824$split_metrics_into_equal_measures__9829:const__8	Lclojure/lang/Keyword;
/*    */     //   474: aastore
/*    */     //   475: dup
/*    */     //   476: iconst_3
/*    */     //   477: aload_0
/*    */     //   478: getfield 26	aeolian/composer$fn__9824$split_metrics_into_equal_measures__9829:output_schema9819	Ljava/lang/Object;
/*    */     //   481: aastore
/*    */     //   482: dup
/*    */     //   483: iconst_4
/*    */     //   484: getstatic 102	aeolian/composer$fn__9824$split_metrics_into_equal_measures__9829:const__9	Lclojure/lang/Keyword;
/*    */     //   487: aastore
/*    */     //   488: dup
/*    */     //   489: iconst_5
/*    */     //   490: aload_3
/*    */     //   491: aastore
/*    */     //   492: dup
/*    */     //   493: bipush 6
/*    */     //   495: getstatic 105	aeolian/composer$fn__9824$split_metrics_into_equal_measures__9829:const__10	Lclojure/lang/Keyword;
/*    */     //   498: aastore
/*    */     //   499: dup
/*    */     //   500: bipush 7
/*    */     //   502: aload 5
/*    */     //   504: aconst_null
/*    */     //   505: astore 5
/*    */     //   507: aastore
/*    */     //   508: invokestatic 111	clojure/lang/RT:mapUniqueKeys	([Ljava/lang/Object;)Lclojure/lang/IPersistentMap;
/*    */     //   511: checkcast 113	clojure/lang/IPersistentMap
/*    */     //   514: invokespecial 116	clojure/lang/ExceptionInfo:<init>	(Ljava/lang/String;Lclojure/lang/IPersistentMap;)V
/*    */     //   517: checkcast 118	java/lang/Throwable
/*    */     //   520: athrow
/*    */     //   521: goto +6 -> 527
/*    */     //   524: pop
/*    */     //   525: aconst_null
/*    */     //   526: pop
/*    */     //   527: goto +6 -> 533
/*    */     //   530: pop
/*    */     //   531: aconst_null
/*    */     //   532: pop
/*    */     //   533: aload_3
/*    */     //   534: aconst_null
/*    */     //   535: astore_3
/*    */     //   536: areturn
/*    */     // Line number table:
/*    */     //   Java source line #74	-> byte code offset #0
/*    */     //   Java source line #74	-> byte code offset #7
/*    */     //   Java source line #74	-> byte code offset #11
/*    */     //   Java source line #74	-> byte code offset #27
/*    */     //   Java source line #74	-> byte code offset #49
/*    */     //   Java source line #74	-> byte code offset #68
/*    */     //   Java source line #74	-> byte code offset #75
/*    */     //   Java source line #74	-> byte code offset #83
/*    */     //   Java source line #74	-> byte code offset #99
/*    */     //   Java source line #74	-> byte code offset #106
/*    */     //   Java source line #74	-> byte code offset #111
/*    */     //   Java source line #74	-> byte code offset #115
/*    */     //   Java source line #74	-> byte code offset #122
/*    */     //   Java source line #74	-> byte code offset #151
/*    */     //   Java source line #74	-> byte code offset #165
/*    */     //   Java source line #74	-> byte code offset #170
/*    */     //   Java source line #74	-> byte code offset #175
/*    */     //   Java source line #74	-> byte code offset #276
/*    */     //   Java source line #74	-> byte code offset #279
/*    */     //   Java source line #74	-> byte code offset #285
/*    */     //   Java source line #74	-> byte code offset #298
/*    */     //   Java source line #74	-> byte code offset #320
/*    */     //   Java source line #74	-> byte code offset #339
/*    */     //   Java source line #74	-> byte code offset #346
/*    */     //   Java source line #74	-> byte code offset #352
/*    */     //   Java source line #74	-> byte code offset #368
/*    */     //   Java source line #74	-> byte code offset #375
/*    */     //   Java source line #74	-> byte code offset #380
/*    */     //   Java source line #74	-> byte code offset #384
/*    */     //   Java source line #74	-> byte code offset #391
/*    */     //   Java source line #74	-> byte code offset #420
/*    */     //   Java source line #74	-> byte code offset #434
/*    */     //   Java source line #74	-> byte code offset #439
/*    */     //   Java source line #74	-> byte code offset #444
/*    */     // Local variable table:
/*    */     //   start	length	slot	name	signature
/*    */     //   0	536	0	this	Object
/*    */     //   0	536	1	G__9823	Object
/*    */     //   11	525	2	validate__8479__auto__9839	Object
/*    */     //   27	233	3	args__8480__auto__9835	Object
/*    */     //   285	251	3	o__8482__auto__9838	Object
/*    */     //   122	138	4	temp__4657__auto__9834	Object
/*    */     //   391	136	4	temp__4657__auto__9837	Object
/*    */     //   141	113	5	error__8481__auto__9833	Object
/*    */     //   410	111	5	error__8481__auto__9836	Object
/*    */   }
/*    */ }


/* Location:              /home/amarks/code/aeolian/target/aeolian-0.1.1-SNAPSHOT.jar!/aeolian/composer$fn__9824$split_metrics_into_equal_measures__9829.class
 * Java compiler version: 5 (49.0)
 * JD-Core Version:       0.7.1
 */