/*   */ package aeolian; import clojure.lang.AFn;
/*   */ 
/* 1 */ public final class core$loading__5569__auto____36 extends clojure.lang.AFunction { public static final AFn const__11 = (AFn)clojure.lang.Tuple.create(clojure.lang.Symbol.intern(null, "clojure.java.io"), clojure.lang.RT.keyword(null, "as"), clojure.lang.Symbol.intern(null, "io")); public static final AFn const__10 = (AFn)clojure.lang.Tuple.create(clojure.lang.Symbol.intern(null, "aeolian.banner"), clojure.lang.RT.keyword(null, "as"), clojure.lang.Symbol.intern(null, "banner")); public static final AFn const__9 = (AFn)clojure.lang.Tuple.create(clojure.lang.Symbol.intern(null, "aeolian.abc.key"), clojure.lang.RT.keyword(null, "as"), clojure.lang.Symbol.intern(null, "k")); public static final AFn const__8 = (AFn)clojure.lang.Tuple.create(clojure.lang.Symbol.intern(null, "aeolian.abc.header"), clojure.lang.RT.keyword(null, "as"), clojure.lang.Symbol.intern(null, "h")); public static final AFn const__7 = (AFn)clojure.lang.Tuple.create(clojure.lang.Symbol.intern(null, "schema.core"), clojure.lang.RT.keyword(null, "as"), clojure.lang.Symbol.intern(null, "s")); public static final AFn const__6 = (AFn)clojure.lang.Tuple.create(clojure.lang.Symbol.intern(null, "taoensso.timbre"), clojure.lang.RT.keyword(null, "as"), clojure.lang.Symbol.intern(null, "log")); public static final AFn const__5 = (AFn)clojure.lang.Tuple.create(clojure.lang.Symbol.intern(null, "aeolian.parser"), clojure.lang.RT.keyword(null, "as"), clojure.lang.Symbol.intern(null, "parser")); public static final AFn const__4 = (AFn)clojure.lang.Tuple.create(clojure.lang.Symbol.intern(null, "aeolian.midi.core"), clojure.lang.RT.keyword(null, "as"), clojure.lang.Symbol.intern(null, "midi")); public static final AFn const__3 = (AFn)clojure.lang.Tuple.create(clojure.lang.Symbol.intern(null, "aeolian.composer"), clojure.lang.RT.keyword(null, "as"), clojure.lang.Symbol.intern(null, "composer")); public static final clojure.lang.Var const__2 = (clojure.lang.Var)clojure.lang.RT.var("clojure.core", "require"); public static final AFn const__1 = (AFn)clojure.lang.Symbol.intern(null, "clojure.core"); public static final clojure.lang.Var const__0 = (clojure.lang.Var)clojure.lang.RT.var("clojure.core", "refer");
/*   */   
/*   */   /* Error */
/*   */   public Object invoke()
/*   */   {
/*   */     // Byte code:
/*   */     //   0: iconst_2
/*   */     //   1: anewarray 13	java/lang/Object
/*   */     //   4: dup
/*   */     //   5: iconst_0
/*   */     //   6: getstatic 19	clojure/lang/Compiler:LOADER	Lclojure/lang/Var;
/*   */     //   9: aastore
/*   */     //   10: dup
/*   */     //   11: iconst_1
/*   */     //   12: aload_0
/*   */     //   13: invokevirtual 23	java/lang/Object:getClass	()Ljava/lang/Class;
/*   */     //   16: checkcast 25	java/lang/Class
/*   */     //   19: invokevirtual 29	java/lang/Class:getClassLoader	()Ljava/lang/ClassLoader;
/*   */     //   22: aastore
/*   */     //   23: invokestatic 35	clojure/lang/RT:mapUniqueKeys	([Ljava/lang/Object;)Lclojure/lang/IPersistentMap;
/*   */     //   26: checkcast 37	clojure/lang/Associative
/*   */     //   29: invokestatic 43	clojure/lang/Var:pushThreadBindings	(Lclojure/lang/Associative;)V
/*   */     //   32: aconst_null
/*   */     //   33: pop
/*   */     //   34: getstatic 46	aeolian/core$loading__5569__auto____36:const__0	Lclojure/lang/Var;
/*   */     //   37: invokevirtual 49	clojure/lang/Var:getRawRoot	()Ljava/lang/Object;
/*   */     //   40: checkcast 51	clojure/lang/IFn
/*   */     //   43: getstatic 55	aeolian/core$loading__5569__auto____36:const__1	Lclojure/lang/AFn;
/*   */     //   46: invokeinterface 58 2 0
/*   */     //   51: pop
/*   */     //   52: getstatic 61	aeolian/core$loading__5569__auto____36:const__2	Lclojure/lang/Var;
/*   */     //   55: invokevirtual 49	clojure/lang/Var:getRawRoot	()Ljava/lang/Object;
/*   */     //   58: checkcast 51	clojure/lang/IFn
/*   */     //   61: getstatic 64	aeolian/core$loading__5569__auto____36:const__3	Lclojure/lang/AFn;
/*   */     //   64: getstatic 67	aeolian/core$loading__5569__auto____36:const__4	Lclojure/lang/AFn;
/*   */     //   67: getstatic 70	aeolian/core$loading__5569__auto____36:const__5	Lclojure/lang/AFn;
/*   */     //   70: getstatic 73	aeolian/core$loading__5569__auto____36:const__6	Lclojure/lang/AFn;
/*   */     //   73: getstatic 76	aeolian/core$loading__5569__auto____36:const__7	Lclojure/lang/AFn;
/*   */     //   76: getstatic 79	aeolian/core$loading__5569__auto____36:const__8	Lclojure/lang/AFn;
/*   */     //   79: getstatic 82	aeolian/core$loading__5569__auto____36:const__9	Lclojure/lang/AFn;
/*   */     //   82: getstatic 85	aeolian/core$loading__5569__auto____36:const__10	Lclojure/lang/AFn;
/*   */     //   85: getstatic 88	aeolian/core$loading__5569__auto____36:const__11	Lclojure/lang/AFn;
/*   */     //   88: invokeinterface 91 10 0
/*   */     //   93: astore_1
/*   */     //   94: invokestatic 94	clojure/lang/Var:popThreadBindings	()V
/*   */     //   97: goto +9 -> 106
/*   */     //   100: astore_2
/*   */     //   101: invokestatic 94	clojure/lang/Var:popThreadBindings	()V
/*   */     //   104: aload_2
/*   */     //   105: athrow
/*   */     //   106: aload_1
/*   */     //   107: areturn
/*   */     // Line number table:
/*   */     //   Java source line #1	-> byte code offset #0
/*   */     //   Java source line #1	-> byte code offset #6
/*   */     //   Java source line #1	-> byte code offset #13
/*   */     //   Java source line #1	-> byte code offset #19
/*   */     //   Java source line #1	-> byte code offset #29
/*   */     //   Java source line #1	-> byte code offset #40
/*   */     //   Java source line #1	-> byte code offset #46
/*   */     //   Java source line #1	-> byte code offset #58
/*   */     //   Java source line #1	-> byte code offset #88
/*   */     //   Java source line #1	-> byte code offset #94
/*   */     //   Java source line #1	-> byte code offset #101
/*   */     // Local variable table:
/*   */     //   start	length	slot	name	signature
/*   */     //   0	107	0	this	Object
/*   */     //   93	14	1	localObject1	Object
/*   */     //   100	5	2	localObject2	Object
/*   */     // Exception table:
/*   */     //   from	to	target	type
/*   */     //   32	94	100	finally
/*   */   }
/*   */ }


/* Location:              /home/amarks/code/aeolian/target/aeolian-0.1.1-SNAPSHOT.jar!/aeolian/core$loading__5569__auto____36.class
 * Java compiler version: 5 (49.0)
 * JD-Core Version:       0.7.1
 */