/*    */ package aeolian.abc;
/*    */ 
/*    */ import clojure.lang.AFn;
/*    */ import clojure.lang.AFunction;
/*    */ import clojure.lang.RT;
/*    */ import clojure.lang.Var;
/*    */ 
/*    */ public final class notes$chord
/*    */   extends AFunction
/*    */ {
/*    */   /* Error */
/*    */   public static Object invokeStatic(Object chord_index, Object composition_key)
/*    */   {
/*    */     // Byte code:
/*    */     //   0: getstatic 15	aeolian/abc/notes$chord:const__1	Lclojure/lang/Var;
/*    */     //   3: invokevirtual 21	clojure/lang/Var:getRawRoot	()Ljava/lang/Object;
/*    */     //   6: aload_1
/*    */     //   7: aconst_null
/*    */     //   8: astore_1
/*    */     //   9: invokestatic 27	clojure/lang/Util:equiv	(Ljava/lang/Object;Ljava/lang/Object;)Z
/*    */     //   12: ifeq +40 -> 52
/*    */     //   15: getstatic 30	aeolian/abc/notes$chord:const__2	Lclojure/lang/Var;
/*    */     //   18: invokevirtual 21	clojure/lang/Var:getRawRoot	()Ljava/lang/Object;
/*    */     //   21: checkcast 32	clojure/lang/IFn
/*    */     //   24: ldc 34
/*    */     //   26: getstatic 38	aeolian/abc/notes$chord:const__4	Lclojure/lang/AFn;
/*    */     //   29: aload_0
/*    */     //   30: aconst_null
/*    */     //   31: astore_0
/*    */     //   32: checkcast 40	java/lang/Number
/*    */     //   35: invokestatic 46	clojure/lang/RT:intCast	(Ljava/lang/Object;)I
/*    */     //   38: invokestatic 50	clojure/lang/RT:nth	(Ljava/lang/Object;I)Ljava/lang/Object;
/*    */     //   41: ldc 34
/*    */     //   43: invokeinterface 54 4 0
/*    */     //   48: goto +37 -> 85
/*    */     //   51: pop
/*    */     //   52: getstatic 30	aeolian/abc/notes$chord:const__2	Lclojure/lang/Var;
/*    */     //   55: invokevirtual 21	clojure/lang/Var:getRawRoot	()Ljava/lang/Object;
/*    */     //   58: checkcast 32	clojure/lang/IFn
/*    */     //   61: ldc 34
/*    */     //   63: getstatic 57	aeolian/abc/notes$chord:const__5	Lclojure/lang/AFn;
/*    */     //   66: aload_0
/*    */     //   67: aconst_null
/*    */     //   68: astore_0
/*    */     //   69: checkcast 40	java/lang/Number
/*    */     //   72: invokestatic 46	clojure/lang/RT:intCast	(Ljava/lang/Object;)I
/*    */     //   75: invokestatic 50	clojure/lang/RT:nth	(Ljava/lang/Object;I)Ljava/lang/Object;
/*    */     //   78: ldc 34
/*    */     //   80: invokeinterface 54 4 0
/*    */     //   85: areturn
/*    */     // Line number table:
/*    */     //   Java source line #21	-> byte code offset #0
/*    */     //   Java source line #22	-> byte code offset #0
/*    */     //   Java source line #22	-> byte code offset #9
/*    */     //   Java source line #23	-> byte code offset #21
/*    */     //   Java source line #23	-> byte code offset #38
/*    */     //   Java source line #23	-> byte code offset #43
/*    */     //   Java source line #24	-> byte code offset #58
/*    */     //   Java source line #24	-> byte code offset #75
/*    */     //   Java source line #24	-> byte code offset #80
/*    */     // Local variable table:
/*    */     //   start	length	slot	name	signature
/*    */     //   0	85	0	chord_index	Object
/*    */     //   0	85	1	composition_key	Object
/*    */   }
/*    */   
/*    */   public Object invoke(Object paramObject1, Object paramObject2)
/*    */   {
/* 21 */     paramObject1 = null;paramObject2 = null;return invokeStatic(paramObject1, paramObject2); } public static final AFn const__5 = (AFn)RT.vector(new Object[] { "Cm", "Ddim", "_E", "Fm", "Gm", "_A+", "_B+" }); public static final AFn const__4 = (AFn)RT.vector(new Object[] { "C", "Dm", "Em", "F", "G", "A+", "B+" }); public static final Var const__2 = (Var)RT.var("clojure.core", "str"); public static final Var const__1 = (Var)RT.var("aeolian.abc.key", "major");
/*    */ }


/* Location:              /home/amarks/code/aeolian/target/aeolian-0.1.1-SNAPSHOT.jar!/aeolian/abc/notes$chord.class
 * Java compiler version: 5 (49.0)
 * JD-Core Version:       0.7.1
 */